{
    "system":{
        "Welcome":"Welcome here",
        "Leave":"Just left us",
        "Kick":"Was kicked from this server",
        "Report":"Was report",
        "Perms":"You don't have permission for this command",
        "Error":"Unexpected error!",
        "NoneReport":"No reports we're found"
    },
    "usage" : {
        "kick":"Please use !kick <player> <reason>",
        "ban":"Please use !ban <player> <reason>",
        "report":"Please use !report <player> <reason>",
        "clear":"Please use !clear <index>"
    },
    "erros":{
        "bot":"You can't interact with bot!"
    },
    "room":{
        "bot":"Plese use this command in 'Commands Room",
        "admin":"Please use this command in 'Admin Room'",
        "report":"Please use this command in 'Report room'"
    }
}   
